odoo10_addon_sale_invoice_auto_deliver-10.0.1.0.1-py3.8-nspkg.pth
odoo/addons/sale_invoice_auto_deliver/README.rst
odoo/addons/sale_invoice_auto_deliver/__init__.py
odoo/addons/sale_invoice_auto_deliver/__manifest__.py
odoo/addons/sale_invoice_auto_deliver/i18n/ca.po
odoo/addons/sale_invoice_auto_deliver/i18n/es.po
odoo/addons/sale_invoice_auto_deliver/i18n/fr.po
odoo/addons/sale_invoice_auto_deliver/i18n/sale_invoice_auto_deliver.pot
odoo/addons/sale_invoice_auto_deliver/readme/CONTRIBUTORS.rst
odoo/addons/sale_invoice_auto_deliver/readme/DESCRIPTION.rst
odoo/addons/sale_invoice_auto_deliver/readme/USAGE.rst
odoo/addons/sale_invoice_auto_deliver/static/description/icon.png
odoo/addons/sale_invoice_auto_deliver/static/description/index.html
odoo/addons/sale_invoice_auto_deliver/tests/__init__.py
odoo/addons/sale_invoice_auto_deliver/tests/test_sale_invoice_auto_deliver.py
odoo/addons/sale_invoice_auto_deliver/wizards/__init__.py
odoo/addons/sale_invoice_auto_deliver/wizards/sale_make_invoice_advance.py
odoo10_addon_sale_invoice_auto_deliver-10.0.1.0.1.dist-info/METADATA
odoo10_addon_sale_invoice_auto_deliver-10.0.1.0.1.dist-info/WHEEL
odoo10_addon_sale_invoice_auto_deliver-10.0.1.0.1.dist-info/namespace_packages.txt
odoo10_addon_sale_invoice_auto_deliver-10.0.1.0.1.dist-info/top_level.txt
odoo10_addon_sale_invoice_auto_deliver-10.0.1.0.1.dist-info/RECORD
